{
  "id": "scenario-value-scanner-parent-scenarios-workplace-organizational-parental leave recognized as essential workplace benefit",
  "contentType": "scenario",
  "title": "Parental leave recognized as essential workplace benefit",
  "description": "Parental leave recognized as essential workplace benefit",
  "content": "Scenario: Parental leave recognized as essential workplace benefit\n    Given parents need time for infant care, adoption, family crisis\n    And parental leave is essential for child well-being\n    When the workplace_elohim assesses workplace policies\n    Then it should flag inadequate parental leave as care economy violation\n    And it should help Sarah advocate for better leave policies\n    And the system should recognize parental leave as basic necessity\n    And workplace should provide substantial paid parental leave\n    And care economy principles should require workplace support for new parents\n    And Sarah should have support for advocating for family leave\n",
  "contentFormat": "gherkin",
  "tags": [
    "epic:value_scanner",
    "user_type:parent",
    "governance_layer:workplace_organizational",
    "related_users:worker,employer,colleague,child",
    "related_layers:individual,household,family",
    "elohim_agents:personal_agent,workplace_elohim",
    "value-scanner",
    "scenario"
  ],
  "sourcePath": "value_scanner/parent/scenarios/workplace_organizational.feature",
  "relatedNodeIds": [
    "feature-value-scanner-parent-scenarios-workplace-organizational",
    "value-scanner-epic"
  ],
  "metadata": {
    "category": "value-scanner",
    "featureId": "feature-value-scanner-parent-scenarios-workplace-organizational",
    "epic": "value_scanner"
  },
  "createdAt": "2025-11-21T18:54:29.194597",
  "updatedAt": "2025-11-21T18:54:29.194597"
}