{
  "id": "scenario-value-scanner-idd-community-scenarios-family-managing financial oversight with dignity",
  "contentType": "scenario",
  "title": "Managing financial oversight with dignity",
  "description": "Managing financial oversight with dignity",
  "content": "Scenario: Managing financial oversight with dignity\n    Given Jordan's parents have financial guardianship\n    And Jordan is learning money management skills\n    When Jordan makes purchases with their allowance\n    Then the personal_agent helps Jordan track spending\n    And parents can monitor for safety without controlling every choice\n    And Jordan has autonomy within appropriate boundaries\n    And the family_elohim balances oversight with independence\n    And Jordan's financial learning is supported, not prevented\n    And Jordan experiences growing financial autonomy\n",
  "contentFormat": "gherkin",
  "tags": [
    "value-scanner",
    "scenario"
  ],
  "sourcePath": "value_scanner/idd_community/scenarios/family.feature",
  "relatedNodeIds": [
    "feature-value-scanner-idd-community-scenarios-family"
  ],
  "metadata": {
    "category": "value-scanner",
    "featureId": "feature-value-scanner-idd-community-scenarios-family",
    "epic": null
  },
  "createdAt": "2025-11-21T18:54:29.191597",
  "updatedAt": "2025-11-21T18:54:29.191597"
}