{
  "id": "scenario-value-scanner-single-parent-scenarios-household-household care tokens include supplements for single-parent resource constraints",
  "contentType": "scenario",
  "title": "Household care tokens include supplements for single-parent resource constraints",
  "description": "Household care tokens include supplements for single-parent resource constraints",
  "content": "Scenario: Household care tokens include supplements for single-parent resource constraints\n    Given Maria's household operates on severely limited income\n    And the Value Scanner should be accessible regardless of economic status\n    When household care tokens are calculated\n    Then Maria should receive care token supplements based on income level\n    And her single-parent status should qualify for enhanced support\n    And supplements should enable continued participation without financial barrier\n    And care economy should function as economic support system\n    And access should be dignified, never requiring means-tested humiliation\n",
  "contentFormat": "gherkin",
  "tags": [
    "epic:value_scanner",
    "user_type:single_parent",
    "governance_layer:household",
    "related_users:parent,child,young_child,preteen,teen",
    "related_layers:individual,family,community",
    "elohim_agents:personal_agent,household_elohim",
    "value-scanner",
    "scenario"
  ],
  "sourcePath": "value_scanner/single_parent/scenarios/household.feature",
  "relatedNodeIds": [
    "feature-value-scanner-single-parent-scenarios-household",
    "value-scanner-epic"
  ],
  "metadata": {
    "category": "value-scanner",
    "featureId": "feature-value-scanner-single-parent-scenarios-household",
    "epic": "value_scanner"
  },
  "createdAt": "2025-11-21T18:54:29.196597",
  "updatedAt": "2025-11-21T18:54:29.196597"
}